{
  "date": "09-06",
  "actors": [
    {
      "id": 207228,
      "name": "Tylor Chase",
      "profilePath": null,
      "birthday": "1989-09-06",
      "popularity": 11.2402,
      "baconNumber": 2
    },
    {
      "id": 17605,
      "name": "Idris Elba",
      "profilePath": "/be1bVF7qGX91a6c5WeRPs5pKXln.jpg",
      "birthday": "1972-09-06",
      "popularity": 5.7845,
      "baconNumber": 2
    },
    {
      "id": 2146942,
      "name": "Freya Allan",
      "profilePath": "/8RuLG2mePw8YgFNUjWROBuxMrwT.jpg",
      "birthday": "2001-09-06",
      "popularity": 4.9342,
      "baconNumber": 2
    },
    {
      "id": 1861484,
      "name": "Aishwarya Lekshmi",
      "profilePath": "/b3yxjhc62X0JZghaRTYNMVrI78a.jpg",
      "birthday": "1991-09-06",
      "popularity": 3.8304,
      "baconNumber": 3
    },
    {
      "id": 1475808,
      "name": "Maddie Phillips",
      "profilePath": "/uuQBuEdkhgDSJ2wnE5N4tyryl4t.jpg",
      "birthday": "1994-09-06",
      "popularity": 3.4833,
      "baconNumber": 2
    },
    {
      "id": 2038,
      "name": "Naomie Harris",
      "profilePath": "/41TVAcYqKKF7PGf3x7QfaLvkLSW.jpg",
      "birthday": "1976-09-06",
      "popularity": 2.4539,
      "baconNumber": 2
    },
    {
      "id": 1607522,
      "name": "Jovan Adepo",
      "profilePath": "/aJcuEbYru85meNGzM0oSeW3nsd6.jpg",
      "birthday": "1988-09-06",
      "popularity": 2.3484,
      "baconNumber": 2
    },
    {
      "id": 95517,
      "name": "Justina Machado",
      "profilePath": "/wAEFYr8rQEoSRm99tLPDiwzuIwU.jpg",
      "birthday": "1972-09-06",
      "popularity": 2.0667,
      "baconNumber": 2
    },
    {
      "id": 2465,
      "name": "James Robinson",
      "profilePath": "/zESqY8KKwkTsuEx75n7Jaumn8ho.jpg",
      "birthday": "1983-09-06",
      "popularity": 2.0559,
      "baconNumber": 3
    },
    {
      "id": 216425,
      "name": "Bertie Carvel",
      "profilePath": "/hahxQXeqj09AHcQRubde19XlBcy.jpg",
      "birthday": "1977-09-06",
      "popularity": 1.6813,
      "baconNumber": 2
    },
    {
      "id": 23874,
      "name": "Phillip Jarrett",
      "profilePath": "/cuuwVsIFPxi6LYyzNN7vRcdpLIr.jpg",
      "birthday": "1959-09-06",
      "popularity": 1.67,
      "baconNumber": 2
    },
    {
      "id": 1736257,
      "name": "Li Yitong",
      "profilePath": "/diMg7nMikWo06tmNqecHCkUOaj5.jpg",
      "birthday": "1990-09-06",
      "popularity": 2.7603
    },
    {
      "id": 2683711,
      "name": "Chang Huasen",
      "profilePath": "/6F0qlEZS0xqgxU5lQlRqS2SiUYL.jpg",
      "birthday": "1997-09-06",
      "popularity": 2.4813
    },
    {
      "id": 550876,
      "name": "Mayuko Sasaki",
      "profilePath": "/3SLMYw8kYB9Ubv7yEFVUMVCamj6.jpg",
      "birthday": "1970-09-06",
      "popularity": 2.4126
    },
    {
      "id": 1509899,
      "name": "Pearce Joza",
      "profilePath": "/7ZjPFJYOZOQ4vM0et06S2x0L16F.jpg",
      "birthday": "2002-09-06",
      "popularity": 2.3205
    },
    {
      "id": 587665,
      "name": "Jun Izumi",
      "profilePath": "/lorlB8ptx9zv6FzurFXXcJNKouZ.jpg",
      "birthday": "1956-09-06",
      "popularity": 2.2351
    },
    {
      "id": 2673,
      "name": "John Ridgely",
      "profilePath": "/gsngEYbN6cn90gZPPeBe7mnUr60.jpg",
      "birthday": "1909-09-06",
      "popularity": 2.2046
    },
    {
      "id": 26728,
      "name": "Sam Hui",
      "profilePath": "/4q095b2EC8U9hEofahPPsLMik9T.jpg",
      "birthday": "1948-09-06",
      "popularity": 2.1656
    },
    {
      "id": 1131910,
      "name": "Raymond Keane",
      "profilePath": "/akwhRWqpBQYm6Ii1qjDObachfnb.jpg",
      "birthday": "1906-09-06",
      "popularity": 2.0309
    },
    {
      "id": 1032103,
      "name": "Rakesh Roshan",
      "profilePath": "/x9PsR3B00EIppvK1Kb0MdbNZyzi.jpg",
      "birthday": "1949-09-06",
      "popularity": 2.013
    },
    {
      "id": 130570,
      "name": "Monica Mok Siu-Kei",
      "profilePath": "/zaCuXunLyZDU1twg90GLTyC7TpZ.jpg",
      "birthday": "1981-09-06",
      "popularity": 1.9395
    },
    {
      "id": 2023196,
      "name": "Aina Yamada",
      "profilePath": "/eytG09sAvIrJ9WlRcrFcYQF4451.jpg",
      "birthday": "1998-09-06",
      "popularity": 1.8706
    },
    {
      "id": 550612,
      "name": "Go Nagai",
      "profilePath": "/4O0lqdSDEJOXCss0sYJDAZEbyZ4.jpg",
      "birthday": "1945-09-06",
      "popularity": 1.7446
    },
    {
      "id": 117508,
      "name": "Kim So-eun",
      "profilePath": "/kXl9W2FGBnHMq2UeCtaYeG1Do4O.jpg",
      "birthday": "1989-09-06",
      "popularity": 1.7442
    }
  ]
}
